<situations>
<situation outs="0" runners="1" balls="0" strikes="0"><total>159591</total><count runs="0">116739</count><count runs="1">23483</count><count runs="2">10620</count><count runs="3">4902</count><count runs="4">2201</count><count runs="5">952</count><count runs="6">420</count><count runs="7">166</count><count runs="8">56</count><count runs="9">32</count><count runs="10">12</count><count runs="11">1</count><count runs="12">2</count><count runs="13">3</count><count runs="14">2</count></situation>
<situation outs="0" runners="1" balls="0" strikes="1"><total>213</total><count runs="0">144</count><count runs="1">35</count><count runs="2">18</count><count runs="3">8</count><count runs="4">6</count><count runs="5">1</count><count runs="6">0</count><count runs="7">0</count><count runs="8">0</count><count runs="9">1</count></situation>
<situation outs="0" runners="1" balls="0" strikes="2"><total>92</total><count runs="0">66</count><count runs="1">14</count><count runs="2">9</count><count runs="3">2</count><count runs="4">1</count></situation>
<situation outs="0" runners="1" balls="1" strikes="0"><total>271</total><count runs="0">170</count><count runs="1">53</count><count runs="2">24</count><count runs="3">11</count><count runs="4">6</count><count runs="5">4</count><count runs="6">1</count><count runs="7">1</count><count runs="8">0</count><count runs="9">1</count></situation>
<situation outs="0" runners="1" balls="1" strikes="1"><total>152</total><count runs="0">102</count><count runs="1">31</count><count runs="2">9</count><count runs="3">4</count><count runs="4">5</count><count runs="5">0</count><count runs="6">0</count><count runs="7">1</count></situation>
<situation outs="0" runners="1" balls="1" strikes="2"><total>85</total><count runs="0">60</count><count runs="1">15</count><count runs="2">5</count><count runs="3">3</count><count runs="4">2</count></situation>
<situation outs="0" runners="1" balls="2" strikes="0"><total>172</total><count runs="0">108</count><count runs="1">28</count><count runs="2">19</count><count runs="3">8</count><count runs="4">4</count><count runs="5">4</count><count runs="6">0</count><count runs="7">0</count><count runs="8">0</count><count runs="9">1</count></situation>
<situation outs="0" runners="1" balls="2" strikes="1"><total>94</total><count runs="0">63</count><count runs="1">22</count><count runs="2">6</count><count runs="3">1</count><count runs="4">2</count></situation>
<situation outs="0" runners="1" balls="2" strikes="2"><total>79</total><count runs="0">60</count><count runs="1">12</count><count runs="2">4</count><count runs="3">1</count><count runs="4">2</count></situation>
<situation outs="0" runners="1" balls="3" strikes="0"><total>129</total><count runs="0">81</count><count runs="1">17</count><count runs="2">16</count><count runs="3">7</count><count runs="4">4</count><count runs="5">4</count></situation>
<situation outs="0" runners="1" balls="3" strikes="1"><total>73</total><count runs="0">51</count><count runs="1">15</count><count runs="2">6</count><count runs="3">1</count></situation>
<situation outs="0" runners="1" balls="3" strikes="2"><total>75</total><count runs="0">54</count><count runs="1">11</count><count runs="2">8</count><count runs="3">1</count><count runs="4">1</count></situation>
<situation outs="0" runners="5" balls="0" strikes="0"><total>3479</total><count runs="0">577</count><count runs="1">1865</count><count runs="2">551</count><count runs="3">261</count><count runs="4">129</count><count runs="5">47</count><count runs="6">29</count><count runs="7">15</count><count runs="8">3</count><count runs="9">2</count></situation>
<situation outs="0" runners="5" balls="1" strikes="0"><total>7</total><count runs="0">0</count><count runs="1">5</count><count runs="2">1</count><count runs="3">1</count></situation>
<situation outs="0" runners="5" balls="2" strikes="0"><total>5</total><count runs="0">0</count><count runs="1">3</count><count runs="2">1</count><count runs="3">1</count></situation>
<situation outs="0" runners="5" balls="3" strikes="0"><total>3</total><count runs="0">0</count><count runs="1">2</count><count runs="2">0</count><count runs="3">1</count></situation>
<situation outs="0" runners="3" balls="0" strikes="0"><total>10003</total><count runs="0">3603</count><count runs="1">3760</count><count runs="2">1401</count><count runs="3">640</count><count runs="4">333</count><count runs="5">166</count><count runs="6">58</count><count runs="7">17</count><count runs="8">17</count><count runs="9">6</count><count runs="10">2</count></situation>
<situation outs="0" runners="3" balls="0" strikes="1"><total>7</total><count runs="0">2</count><count runs="1">4</count><count runs="2">0</count><count runs="3">0</count><count runs="4">0</count><count runs="5">1</count></situation>
<situation outs="0" runners="3" balls="0" strikes="2"><total>2</total><count runs="0">0</count><count runs="1">1</count><count runs="2">0</count><count runs="3">0</count><count runs="4">0</count><count runs="5">1</count></situation>
<situation outs="0" runners="3" balls="1" strikes="0"><total>21</total><count runs="0">13</count><count runs="1">7</count><count runs="2">0</count><count runs="3">1</count></situation>
<situation outs="0" runners="3" balls="1" strikes="1"><total>7</total><count runs="0">5</count><count runs="1">2</count></situation>
<situation outs="0" runners="3" balls="1" strikes="2"><total>4</total><count runs="0">2</count><count runs="1">2</count></situation>
<situation outs="0" runners="3" balls="2" strikes="0"><total>13</total><count runs="0">7</count><count runs="1">5</count><count runs="2">0</count><count runs="3">1</count></situation>
<situation outs="0" runners="3" balls="2" strikes="2"><total>2</total><count runs="0">0</count><count runs="1">2</count></situation>
<situation outs="0" runners="3" balls="3" strikes="0"><total>11</total><count runs="0">6</count><count runs="1">4</count><count runs="2">0</count><count runs="3">1</count></situation>
<situation outs="0" runners="3" balls="3" strikes="1"><total>4</total><count runs="0">3</count><count runs="1">0</count><count runs="2">0</count><count runs="3">1</count></situation>
<situation outs="0" runners="3" balls="3" strikes="2"><total>3</total><count runs="0">0</count><count runs="1">2</count><count runs="2">0</count><count runs="3">1</count></situation>
<situation outs="0" runners="7" balls="0" strikes="0"><total>2389</total><count runs="0">303</count><count runs="1">617</count><count runs="2">772</count><count runs="3">351</count><count runs="4">198</count><count runs="5">84</count><count runs="6">37</count><count runs="7">15</count><count runs="8">8</count><count runs="9">1</count><count runs="10">0</count><count runs="11">1</count><count runs="12">0</count><count runs="13">1</count><count runs="14">1</count></situation>
<situation outs="0" runners="7" balls="0" strikes="1"><total>10</total><count runs="0">2</count><count runs="1">2</count><count runs="2">4</count><count runs="3">0</count><count runs="4">2</count></situation>
<situation outs="0" runners="7" balls="0" strikes="2"><total>7</total><count runs="0">2</count><count runs="1">1</count><count runs="2">2</count><count runs="3">0</count><count runs="4">2</count></situation>
<situation outs="0" runners="7" balls="1" strikes="0"><total>6</total><count runs="0">0</count><count runs="1">1</count><count runs="2">2</count><count runs="3">1</count><count runs="4">1</count><count runs="5">1</count></situation>
<situation outs="0" runners="7" balls="1" strikes="1"><total>5</total><count runs="0">0</count><count runs="1">2</count><count runs="2">2</count><count runs="3">0</count><count runs="4">1</count></situation>
<situation outs="0" runners="7" balls="2" strikes="0"><total>4</total><count runs="0">0</count><count runs="1">0</count><count runs="2">2</count><count runs="3">1</count><count runs="4">0</count><count runs="5">1</count></situation>
<situation outs="0" runners="7" balls="3" strikes="0"><total>3</total><count runs="0">0</count><count runs="1">0</count><count runs="2">2</count><count runs="3">0</count><count runs="4">0</count><count runs="5">1</count></situation>
<situation outs="0" runners="2" balls="0" strikes="0"><total>46410</total><count runs="0">26308</count><count runs="1">9436</count><count runs="2">5522</count><count runs="3">2818</count><count runs="4">1291</count><count runs="5">586</count><count runs="6">275</count><count runs="7">103</count><count runs="8">33</count><count runs="9">20</count><count runs="10">10</count><count runs="11">1</count><count runs="12">2</count><count runs="13">3</count><count runs="14">2</count></situation>
<situation outs="0" runners="2" balls="0" strikes="1"><total>48</total><count runs="0">26</count><count runs="1">6</count><count runs="2">10</count><count runs="3">2</count><count runs="4">1</count><count runs="5">1</count><count runs="6">1</count><count runs="7">1</count></situation>
<situation outs="0" runners="2" balls="0" strikes="2"><total>21</total><count runs="0">9</count><count runs="1">2</count><count runs="2">7</count><count runs="3">0</count><count runs="4">1</count><count runs="5">1</count><count runs="6">0</count><count runs="7">1</count></situation>
<situation outs="0" runners="2" balls="1" strikes="0"><total>66</total><count runs="0">34</count><count runs="1">15</count><count runs="2">12</count><count runs="3">4</count><count runs="4">1</count></situation>
<situation outs="0" runners="2" balls="1" strikes="1"><total>29</total><count runs="0">16</count><count runs="1">6</count><count runs="2">4</count><count runs="3">3</count></situation>
<situation outs="0" runners="2" balls="1" strikes="2"><total>14</total><count runs="0">7</count><count runs="1">2</count><count runs="2">5</count></situation>
<situation outs="0" runners="2" balls="2" strikes="0"><total>37</total><count runs="0">19</count><count runs="1">10</count><count runs="2">5</count><count runs="3">2</count><count runs="4">1</count></situation>
<situation outs="0" runners="2" balls="2" strikes="1"><total>22</total><count runs="0">15</count><count runs="1">4</count><count runs="2">1</count><count runs="3">2</count></situation>
<situation outs="0" runners="2" balls="2" strikes="2"><total>15</total><count runs="0">12</count><count runs="1">1</count><count runs="2">1</count><count runs="3">1</count></situation>
<situation outs="0" runners="2" balls="3" strikes="0"><total>24</total><count runs="0">13</count><count runs="1">5</count><count runs="2">3</count><count runs="3">2</count><count runs="4">1</count></situation>
<situation outs="0" runners="2" balls="3" strikes="1"><total>13</total><count runs="0">10</count><count runs="1">2</count><count runs="2">1</count></situation>
<situation outs="0" runners="2" balls="3" strikes="2"><total>7</total><count runs="0">6</count><count runs="1">0</count><count runs="2">1</count></situation>
<situation outs="0" runners="6" balls="0" strikes="0"><total>4371</total><count runs="0">615</count><count runs="1">1787</count><count runs="2">828</count><count runs="3">569</count><count runs="4">301</count><count runs="5">140</count><count runs="6">76</count><count runs="7">26</count><count runs="8">15</count><count runs="9">9</count><count runs="10">2</count><count runs="11">2</count><count runs="12">0</count><count runs="13">0</count><count runs="14">1</count></situation>
<situation outs="0" runners="6" balls="1" strikes="0"><total>9</total><count runs="0">3</count><count runs="1">5</count><count runs="2">1</count></situation>
<situation outs="0" runners="6" balls="2" strikes="0"><total>7</total><count runs="0">2</count><count runs="1">4</count><count runs="2">1</count></situation>
<situation outs="0" runners="6" balls="3" strikes="0"><total>5</total><count runs="0">2</count><count runs="1">2</count><count runs="2">1</count></situation>
<situation outs="0" runners="4" balls="0" strikes="0"><total>9916</total><count runs="0">3314</count><count runs="1">2238</count><count runs="2">1861</count><count runs="3">1262</count><count runs="4">664</count><count runs="5">322</count><count runs="6">150</count><count runs="7">60</count><count runs="8">20</count><count runs="9">13</count><count runs="10">10</count><count runs="11">0</count><count runs="12">1</count><count runs="13">1</count></situation>
<situation outs="0" runners="4" balls="0" strikes="1"><total>20</total><count runs="0">10</count><count runs="1">3</count><count runs="2">4</count><count runs="3">2</count><count runs="4">1</count></situation>
<situation outs="0" runners="4" balls="0" strikes="2"><total>11</total><count runs="0">4</count><count runs="1">1</count><count runs="2">4</count><count runs="3">1</count><count runs="4">1</count></situation>
<situation outs="0" runners="4" balls="1" strikes="0"><total>26</total><count runs="0">3</count><count runs="1">4</count><count runs="2">6</count><count runs="3">7</count><count runs="4">4</count><count runs="5">1</count><count runs="6">1</count></situation>
<situation outs="0" runners="4" balls="1" strikes="1"><total>9</total><count runs="0">3</count><count runs="1">1</count><count runs="2">0</count><count runs="3">3</count><count runs="4">1</count><count runs="5">1</count></situation>
<situation outs="0" runners="4" balls="2" strikes="0"><total>17</total><count runs="0">3</count><count runs="1">2</count><count runs="2">5</count><count runs="3">3</count><count runs="4">3</count><count runs="5">0</count><count runs="6">1</count></situation>
<situation outs="0" runners="4" balls="2" strikes="1"><total>9</total><count runs="0">0</count><count runs="1">1</count><count runs="2">1</count><count runs="3">1</count><count runs="4">4</count><count runs="5">1</count><count runs="6">1</count></situation>
<situation outs="0" runners="4" balls="3" strikes="0"><total>10</total><count runs="0">3</count><count runs="1">1</count><count runs="2">4</count><count runs="3">2</count></situation>
<situation outs="0" runners="4" balls="3" strikes="1"><total>11</total><count runs="0">2</count><count runs="1">1</count><count runs="2">3</count><count runs="3">1</count><count runs="4">3</count><count runs="5">1</count></situation>
<situation outs="0" runners="4" balls="3" strikes="2"><total>8</total><count runs="0">3</count><count runs="1">0</count><count runs="2">3</count><count runs="3">0</count><count runs="4">2</count></situation>
<situation outs="0" runners="8" balls="0" strikes="0"><total>2693</total><count runs="0">355</count><count runs="1">620</count><count runs="2">542</count><count runs="3">478</count><count runs="4">366</count><count runs="5">179</count><count runs="6">75</count><count runs="7">41</count><count runs="8">17</count><count runs="9">12</count><count runs="10">6</count><count runs="11">0</count><count runs="12">0</count><count runs="13">1</count><count runs="14">1</count></situation>
<situation outs="0" runners="8" balls="0" strikes="1"><total>4</total><count runs="0">0</count><count runs="1">1</count><count runs="2">3</count></situation>
<situation outs="0" runners="8" balls="1" strikes="0"><total>8</total><count runs="0">1</count><count runs="1">0</count><count runs="2">3</count><count runs="3">0</count><count runs="4">3</count><count runs="5">1</count></situation>
<situation outs="0" runners="8" balls="1" strikes="1"><total>5</total><count runs="0">1</count><count runs="1">1</count><count runs="2">1</count><count runs="3">0</count><count runs="4">1</count><count runs="5">1</count></situation>
<situation outs="0" runners="8" balls="1" strikes="2"><total>4</total><count runs="0">1</count><count runs="1">1</count><count runs="2">2</count></situation>
<situation outs="0" runners="8" balls="2" strikes="0"><total>4</total><count runs="0">0</count><count runs="1">0</count><count runs="2">2</count><count runs="3">0</count><count runs="4">2</count></situation>
<situation outs="0" runners="8" balls="2" strikes="2"><total>3</total><count runs="0">0</count><count runs="1">1</count><count runs="2">0</count><count runs="3">0</count><count runs="4">1</count><count runs="5">1</count></situation>
<situation outs="1" runners="1" balls="0" strikes="0"><total>107964</total><count runs="0">91767</count><count runs="1">9774</count><count runs="2">3884</count><count runs="3">1530</count><count runs="4">622</count><count runs="5">243</count><count runs="6">87</count><count runs="7">42</count><count runs="8">7</count><count runs="9">7</count><count runs="10">1</count></situation>
<situation outs="1" runners="1" balls="0" strikes="1"><total>133</total><count runs="0">107</count><count runs="1">17</count><count runs="2">8</count><count runs="3">1</count></situation>
<situation outs="1" runners="1" balls="0" strikes="2"><total>80</total><count runs="0">68</count><count runs="1">7</count><count runs="2">5</count></situation>
<situation outs="1" runners="1" balls="1" strikes="0"><total>161</total><count runs="0">130</count><count runs="1">16</count><count runs="2">9</count><count runs="3">3</count><count runs="4">3</count></situation>
<situation outs="1" runners="1" balls="1" strikes="1"><total>91</total><count runs="0">71</count><count runs="1">10</count><count runs="2">5</count><count runs="3">4</count><count runs="4">1</count></situation>
<situation outs="1" runners="1" balls="1" strikes="2"><total>54</total><count runs="0">45</count><count runs="1">7</count><count runs="2">1</count><count runs="3">1</count></situation>
<situation outs="1" runners="1" balls="2" strikes="0"><total>90</total><count runs="0">72</count><count runs="1">10</count><count runs="2">6</count><count runs="3">0</count><count runs="4">2</count></situation>
<situation outs="1" runners="1" balls="2" strikes="1"><total>58</total><count runs="0">44</count><count runs="1">6</count><count runs="2">5</count><count runs="3">2</count><count runs="4">1</count></situation>
<situation outs="1" runners="1" balls="2" strikes="2"><total>54</total><count runs="0">40</count><count runs="1">6</count><count runs="2">5</count><count runs="3">3</count></situation>
<situation outs="1" runners="1" balls="3" strikes="0"><total>53</total><count runs="0">47</count><count runs="1">4</count><count runs="2">1</count><count runs="3">0</count><count runs="4">1</count></situation>
<situation outs="1" runners="1" balls="3" strikes="1"><total>41</total><count runs="0">33</count><count runs="1">6</count><count runs="2">1</count><count runs="3">0</count><count runs="4">1</count></situation>
<situation outs="1" runners="1" balls="3" strikes="2"><total>43</total><count runs="0">31</count><count runs="1">7</count><count runs="2">3</count><count runs="3">2</count></situation>
<situation outs="1" runners="5" balls="0" strikes="0"><total>9958</total><count runs="0">3255</count><count runs="1">4994</count><count runs="2">1018</count><count runs="3">398</count><count runs="4">175</count><count runs="5">77</count><count runs="6">23</count><count runs="7">11</count><count runs="8">5</count><count runs="9">0</count><count runs="10">0</count><count runs="11">2</count></situation>
<situation outs="1" runners="5" balls="0" strikes="1"><total>8</total><count runs="0">3</count><count runs="1">5</count></situation>
<situation outs="1" runners="5" balls="1" strikes="0"><total>14</total><count runs="0">2</count><count runs="1">6</count><count runs="2">5</count><count runs="3">0</count><count runs="4">1</count></situation>
<situation outs="1" runners="5" balls="1" strikes="1"><total>8</total><count runs="0">4</count><count runs="1">3</count><count runs="2">1</count></situation>
<situation outs="1" runners="5" balls="1" strikes="2"><total>7</total><count runs="0">2</count><count runs="1">4</count><count runs="2">1</count></situation>
<situation outs="1" runners="5" balls="2" strikes="0"><total>10</total><count runs="0">1</count><count runs="1">4</count><count runs="2">4</count><count runs="3">0</count><count runs="4">1</count></situation>
<situation outs="1" runners="5" balls="3" strikes="0"><total>9</total><count runs="0">1</count><count runs="1">4</count><count runs="2">3</count><count runs="3">0</count><count runs="4">1</count></situation>
<situation outs="1" runners="5" balls="3" strikes="1"><total>3</total><count runs="0">1</count><count runs="1">2</count></situation>
<situation outs="1" runners="3" balls="0" strikes="0"><total>24798</total><count runs="0">14011</count><count runs="1">6972</count><count runs="2">2295</count><count runs="3">909</count><count runs="4">371</count><count runs="5">151</count><count runs="6">55</count><count runs="7">25</count><count runs="8">3</count><count runs="9">4</count><count runs="10">0</count><count runs="11">1</count><count runs="12">1</count></situation>
<situation outs="1" runners="3" balls="0" strikes="1"><total>36</total><count runs="0">22</count><count runs="1">10</count><count runs="2">2</count><count runs="3">2</count></situation>
<situation outs="1" runners="3" balls="0" strikes="2"><total>16</total><count runs="0">12</count><count runs="1">3</count><count runs="2">1</count></situation>
<situation outs="1" runners="3" balls="1" strikes="0"><total>60</total><count runs="0">29</count><count runs="1">17</count><count runs="2">7</count><count runs="3">4</count><count runs="4">2</count><count runs="5">1</count></situation>
<situation outs="1" runners="3" balls="1" strikes="1"><total>40</total><count runs="0">20</count><count runs="1">12</count><count runs="2">4</count><count runs="3">4</count></situation>
<situation outs="1" runners="3" balls="1" strikes="2"><total>19</total><count runs="0">11</count><count runs="1">5</count><count runs="2">3</count></situation>
<situation outs="1" runners="3" balls="2" strikes="0"><total>30</total><count runs="0">14</count><count runs="1">8</count><count runs="2">3</count><count runs="3">2</count><count runs="4">2</count><count runs="5">1</count></situation>
<situation outs="1" runners="3" balls="2" strikes="1"><total>27</total><count runs="0">14</count><count runs="1">8</count><count runs="2">0</count><count runs="3">4</count><count runs="4">0</count><count runs="5">1</count></situation>
<situation outs="1" runners="3" balls="2" strikes="2"><total>16</total><count runs="0">9</count><count runs="1">2</count><count runs="2">3</count><count runs="3">2</count></situation>
<situation outs="1" runners="3" balls="3" strikes="0"><total>23</total><count runs="0">12</count><count runs="1">6</count><count runs="2">2</count><count runs="3">1</count><count runs="4">2</count></situation>
<situation outs="1" runners="3" balls="3" strikes="1"><total>16</total><count runs="0">9</count><count runs="1">3</count><count runs="2">0</count><count runs="3">2</count><count runs="4">1</count><count runs="5">1</count></situation>
<situation outs="1" runners="3" balls="3" strikes="2"><total>18</total><count runs="0">10</count><count runs="1">1</count><count runs="2">3</count><count runs="3">4</count></situation>
<situation outs="1" runners="7" balls="0" strikes="0"><total>7891</total><count runs="0">2310</count><count runs="1">2023</count><count runs="2">2131</count><count runs="3">840</count><count runs="4">361</count><count runs="5">138</count><count runs="6">57</count><count runs="7">21</count><count runs="8">6</count><count runs="9">1</count><count runs="10">1</count><count runs="11">1</count><count runs="12">0</count><count runs="13">1</count></situation>
<situation outs="1" runners="7" balls="0" strikes="1"><total>9</total><count runs="0">3</count><count runs="1">2</count><count runs="2">2</count><count runs="3">2</count></situation>
<situation outs="1" runners="7" balls="1" strikes="0"><total>10</total><count runs="0">3</count><count runs="1">2</count><count runs="2">2</count><count runs="3">1</count><count runs="4">2</count></situation>
<situation outs="1" runners="7" balls="1" strikes="1"><total>6</total><count runs="0">2</count><count runs="1">1</count><count runs="2">2</count><count runs="3">1</count></situation>
<situation outs="1" runners="7" balls="1" strikes="2"><total>1</total><count runs="0">1</count></situation>
<situation outs="1" runners="7" balls="2" strikes="0"><total>7</total><count runs="0">2</count><count runs="1">2</count><count runs="2">1</count><count runs="3">1</count><count runs="4">1</count></situation>
<situation outs="1" runners="7" balls="2" strikes="1"><total>5</total><count runs="0">1</count><count runs="1">1</count><count runs="2">2</count><count runs="3">1</count></situation>
<situation outs="1" runners="7" balls="3" strikes="0"><total>6</total><count runs="0">2</count><count runs="1">2</count><count runs="2">1</count><count runs="3">0</count><count runs="4">1</count></situation>
<situation outs="1" runners="7" balls="3" strikes="1"><total>4</total><count runs="0">1</count><count runs="1">1</count><count runs="2">2</count></situation>
<situation outs="1" runners="2" balls="0" strikes="0"><total>52290</total><count runs="0">37981</count><count runs="1">7223</count><count runs="2">4086</count><count runs="3">1821</count><count runs="4">699</count><count runs="5">307</count><count runs="6">99</count><count runs="7">49</count><count runs="8">12</count><count runs="9">7</count><count runs="10">4</count><count runs="11">0</count><count runs="12">0</count><count runs="13">2</count></situation>
<situation outs="1" runners="2" balls="0" strikes="1"><total>98</total><count runs="0">64</count><count runs="1">15</count><count runs="2">13</count><count runs="3">3</count><count runs="4">1</count><count runs="5">2</count></situation>
<situation outs="1" runners="2" balls="0" strikes="2"><total>45</total><count runs="0">30</count><count runs="1">6</count><count runs="2">7</count><count runs="3">2</count></situation>
<situation outs="1" runners="2" balls="1" strikes="0"><total>106</total><count runs="0">62</count><count runs="1">20</count><count runs="2">15</count><count runs="3">5</count><count runs="4">2</count><count runs="5">1</count><count runs="6">0</count><count runs="7">1</count></situation>
<situation outs="1" runners="2" balls="1" strikes="1"><total>74</total><count runs="0">49</count><count runs="1">11</count><count runs="2">10</count><count runs="3">1</count><count runs="4">0</count><count runs="5">2</count><count runs="6">0</count><count runs="7">1</count></situation>
<situation outs="1" runners="2" balls="1" strikes="2"><total>43</total><count runs="0">33</count><count runs="1">3</count><count runs="2">7</count></situation>
<situation outs="1" runners="2" balls="2" strikes="0"><total>55</total><count runs="0">26</count><count runs="1">13</count><count runs="2">9</count><count runs="3">4</count><count runs="4">2</count><count runs="5">1</count></situation>
<situation outs="1" runners="2" balls="2" strikes="1"><total>55</total><count runs="0">36</count><count runs="1">6</count><count runs="2">7</count><count runs="3">3</count><count runs="4">0</count><count runs="5">2</count><count runs="6">0</count><count runs="7">1</count></situation>
<situation outs="1" runners="2" balls="2" strikes="2"><total>42</total><count runs="0">31</count><count runs="1">4</count><count runs="2">7</count></situation>
<situation outs="1" runners="2" balls="3" strikes="0"><total>29</total><count runs="0">13</count><count runs="1">8</count><count runs="2">4</count><count runs="3">2</count><count runs="4">2</count></situation>
<situation outs="1" runners="2" balls="3" strikes="1"><total>27</total><count runs="0">15</count><count runs="1">2</count><count runs="2">4</count><count runs="3">4</count><count runs="4">0</count><count runs="5">1</count><count runs="6">0</count><count runs="7">1</count></situation>
<situation outs="1" runners="2" balls="3" strikes="2"><total>33</total><count runs="0">22</count><count runs="1">2</count><count runs="2">6</count><count runs="3">3</count></situation>
<situation outs="1" runners="6" balls="0" strikes="0"><total>9573</total><count runs="0">2982</count><count runs="1">3786</count><count runs="2">1394</count><count runs="3">815</count><count runs="4">338</count><count runs="5">163</count><count runs="6">54</count><count runs="7">27</count><count runs="8">6</count><count runs="9">6</count><count runs="10">2</count></situation>
<situation outs="1" runners="6" balls="0" strikes="1"><total>16</total><count runs="0">7</count><count runs="1">3</count><count runs="2">3</count><count runs="3">2</count><count runs="4">0</count><count runs="5">1</count></situation>
<situation outs="1" runners="6" balls="0" strikes="2"><total>12</total><count runs="0">7</count><count runs="1">1</count><count runs="2">1</count><count runs="3">2</count><count runs="4">0</count><count runs="5">1</count></situation>
<situation outs="1" runners="6" balls="1" strikes="0"><total>16</total><count runs="0">4</count><count runs="1">5</count><count runs="2">1</count><count runs="3">4</count><count runs="4">1</count><count runs="5">1</count></situation>
<situation outs="1" runners="6" balls="1" strikes="1"><total>10</total><count runs="0">2</count><count runs="1">3</count><count runs="2">2</count><count runs="3">3</count></situation>
<situation outs="1" runners="6" balls="1" strikes="2"><total>8</total><count runs="0">2</count><count runs="1">0</count><count runs="2">2</count><count runs="3">4</count></situation>
<situation outs="1" runners="6" balls="2" strikes="0"><total>6</total><count runs="0">1</count><count runs="1">2</count><count runs="2">0</count><count runs="3">1</count><count runs="4">1</count><count runs="5">1</count></situation>
<situation outs="1" runners="6" balls="2" strikes="1"><total>4</total><count runs="0">0</count><count runs="1">4</count></situation>
<situation outs="1" runners="6" balls="2" strikes="2"><total>5</total><count runs="0">0</count><count runs="1">3</count><count runs="2">1</count><count runs="3">1</count></situation>
<situation outs="1" runners="6" balls="3" strikes="0"><total>4</total><count runs="0">1</count><count runs="1">1</count><count runs="2">0</count><count runs="3">0</count><count runs="4">1</count><count runs="5">1</count></situation>
<situation outs="1" runners="6" balls="3" strikes="2"><total>5</total><count runs="0">0</count><count runs="1">2</count><count runs="2">1</count><count runs="3">1</count><count runs="4">1</count></situation>
<situation outs="1" runners="4" balls="0" strikes="0"><total>17147</total><count runs="0">9433</count><count runs="1">3106</count><count runs="2">2154</count><count runs="3">1439</count><count runs="4">602</count><count runs="5">261</count><count runs="6">87</count><count runs="7">40</count><count runs="8">15</count><count runs="9">6</count><count runs="10">1</count><count runs="11">0</count><count runs="12">0</count><count runs="13">3</count></situation>
<situation outs="1" runners="4" balls="0" strikes="1"><total>20</total><count runs="0">11</count><count runs="1">3</count><count runs="2">2</count><count runs="3">2</count><count runs="4">1</count><count runs="5">1</count></situation>
<situation outs="1" runners="4" balls="0" strikes="2"><total>9</total><count runs="0">6</count><count runs="1">2</count><count runs="2">0</count><count runs="3">0</count><count runs="4">1</count></situation>
<situation outs="1" runners="4" balls="1" strikes="0"><total>33</total><count runs="0">16</count><count runs="1">2</count><count runs="2">6</count><count runs="3">5</count><count runs="4">4</count></situation>
<situation outs="1" runners="4" balls="1" strikes="1"><total>11</total><count runs="0">7</count><count runs="1">1</count><count runs="2">1</count><count runs="3">2</count></situation>
<situation outs="1" runners="4" balls="1" strikes="2"><total>5</total><count runs="0">3</count><count runs="1">0</count><count runs="2">0</count><count runs="3">1</count><count runs="4">1</count></situation>
<situation outs="1" runners="4" balls="2" strikes="0"><total>21</total><count runs="0">10</count><count runs="1">2</count><count runs="2">3</count><count runs="3">2</count><count runs="4">4</count></situation>
<situation outs="1" runners="4" balls="2" strikes="1"><total>11</total><count runs="0">8</count><count runs="1">2</count><count runs="2">0</count><count runs="3">0</count><count runs="4">1</count></situation>
<situation outs="1" runners="4" balls="2" strikes="2"><total>11</total><count runs="0">7</count><count runs="1">1</count><count runs="2">0</count><count runs="3">1</count><count runs="4">2</count></situation>
<situation outs="1" runners="4" balls="3" strikes="0"><total>11</total><count runs="0">5</count><count runs="1">1</count><count runs="2">2</count><count runs="3">1</count><count runs="4">2</count></situation>
<situation outs="1" runners="4" balls="3" strikes="2"><total>7</total><count runs="0">3</count><count runs="1">2</count><count runs="2">0</count><count runs="3">0</count><count runs="4">2</count></situation>
<situation outs="1" runners="8" balls="0" strikes="0"><total>5698</total><count runs="0">1735</count><count runs="1">1493</count><count runs="2">953</count><count runs="3">707</count><count runs="4">465</count><count runs="5">215</count><count runs="6">79</count><count runs="7">37</count><count runs="8">11</count><count runs="9">2</count><count runs="10">0</count><count runs="11">0</count><count runs="12">0</count><count runs="13">1</count></situation>
<situation outs="1" runners="8" balls="0" strikes="1"><total>19</total><count runs="0">8</count><count runs="1">5</count><count runs="2">4</count><count runs="3">2</count></situation>
<situation outs="1" runners="8" balls="0" strikes="2"><total>11</total><count runs="0">6</count><count runs="1">2</count><count runs="2">2</count><count runs="3">1</count></situation>
<situation outs="1" runners="8" balls="1" strikes="0"><total>23</total><count runs="0">2</count><count runs="1">4</count><count runs="2">7</count><count runs="3">2</count><count runs="4">4</count><count runs="5">2</count><count runs="6">1</count><count runs="7">1</count></situation>
<situation outs="1" runners="8" balls="1" strikes="1"><total>9</total><count runs="0">2</count><count runs="1">2</count><count runs="2">3</count><count runs="3">1</count><count runs="4">1</count></situation>
<situation outs="1" runners="8" balls="1" strikes="2"><total>3</total><count runs="0">0</count><count runs="1">1</count><count runs="2">0</count><count runs="3">2</count></situation>
<situation outs="1" runners="8" balls="2" strikes="0"><total>16</total><count runs="0">1</count><count runs="1">2</count><count runs="2">5</count><count runs="3">2</count><count runs="4">2</count><count runs="5">2</count><count runs="6">1</count><count runs="7">1</count></situation>
<situation outs="1" runners="8" balls="2" strikes="1"><total>10</total><count runs="0">1</count><count runs="1">2</count><count runs="2">4</count><count runs="3">0</count><count runs="4">2</count><count runs="5">0</count><count runs="6">1</count></situation>
<situation outs="1" runners="8" balls="2" strikes="2"><total>5</total><count runs="0">1</count><count runs="1">1</count><count runs="2">2</count><count runs="3">0</count><count runs="4">0</count><count runs="5">0</count><count runs="6">1</count></situation>
<situation outs="1" runners="8" balls="3" strikes="0"><total>11</total><count runs="0">1</count><count runs="1">2</count><count runs="2">3</count><count runs="3">2</count><count runs="4">1</count><count runs="5">2</count></situation>
<situation outs="1" runners="8" balls="3" strikes="1"><total>8</total><count runs="0">1</count><count runs="1">0</count><count runs="2">2</count><count runs="3">2</count><count runs="4">2</count><count runs="5">1</count></situation>
<situation outs="1" runners="8" balls="3" strikes="2"><total>7</total><count runs="0">2</count><count runs="1">0</count><count runs="2">1</count><count runs="3">2</count><count runs="4">1</count><count runs="5">1</count></situation>
<situation outs="2" runners="1" balls="0" strikes="0"><total>83163</total><count runs="0">78359</count><count runs="1">3234</count><count runs="2">1049</count><count runs="3">339</count><count runs="4">122</count><count runs="5">39</count><count runs="6">12</count><count runs="7">7</count><count runs="8">1</count><count runs="9">1</count></situation>
<situation outs="2" runners="1" balls="0" strikes="1"><total>131</total><count runs="0">116</count><count runs="1">12</count><count runs="2">2</count><count runs="3">1</count></situation>
<situation outs="2" runners="1" balls="0" strikes="2"><total>63</total><count runs="0">56</count><count runs="1">5</count><count runs="2">1</count><count runs="3">1</count></situation>
<situation outs="2" runners="1" balls="1" strikes="0"><total>203</total><count runs="0">179</count><count runs="1">14</count><count runs="2">5</count><count runs="3">4</count><count runs="4">1</count></situation>
<situation outs="2" runners="1" balls="1" strikes="1"><total>123</total><count runs="0">112</count><count runs="1">7</count><count runs="2">4</count></situation>
<situation outs="2" runners="1" balls="1" strikes="2"><total>68</total><count runs="0">60</count><count runs="1">4</count><count runs="2">3</count><count runs="3">1</count></situation>
<situation outs="2" runners="1" balls="2" strikes="0"><total>104</total><count runs="0">92</count><count runs="1">7</count><count runs="2">1</count><count runs="3">3</count><count runs="4">1</count></situation>
<situation outs="2" runners="1" balls="2" strikes="1"><total>100</total><count runs="0">94</count><count runs="1">4</count><count runs="2">2</count></situation>
<situation outs="2" runners="1" balls="2" strikes="2"><total>78</total><count runs="0">69</count><count runs="1">4</count><count runs="2">4</count><count runs="3">1</count></situation>
<situation outs="2" runners="1" balls="3" strikes="0"><total>53</total><count runs="0">47</count><count runs="1">2</count><count runs="2">1</count><count runs="3">2</count><count runs="4">1</count></situation>
<situation outs="2" runners="1" balls="3" strikes="1"><total>56</total><count runs="0">53</count><count runs="1">3</count></situation>
<situation outs="2" runners="1" balls="3" strikes="2"><total>64</total><count runs="0">56</count><count runs="1">4</count><count runs="2">4</count></situation>
<situation outs="2" runners="5" balls="0" strikes="0"><total>14555</total><count runs="0">10214</count><count runs="1">3465</count><count runs="2">592</count><count runs="3">179</count><count runs="4">67</count><count runs="5">28</count><count runs="6">10</count></situation>
<situation outs="2" runners="5" balls="0" strikes="1"><total>14</total><count runs="0">11</count><count runs="1">3</count></situation>
<situation outs="2" runners="5" balls="0" strikes="2"><total>8</total><count runs="0">6</count><count runs="1">2</count></situation>
<situation outs="2" runners="5" balls="1" strikes="0"><total>26</total><count runs="0">18</count><count runs="1">5</count><count runs="2">3</count></situation>
<situation outs="2" runners="5" balls="1" strikes="1"><total>14</total><count runs="0">9</count><count runs="1">4</count><count runs="2">1</count></situation>
<situation outs="2" runners="5" balls="1" strikes="2"><total>7</total><count runs="0">6</count><count runs="1">1</count></situation>
<situation outs="2" runners="5" balls="2" strikes="0"><total>14</total><count runs="0">10</count><count runs="1">2</count><count runs="2">2</count></situation>
<situation outs="2" runners="5" balls="2" strikes="1"><total>9</total><count runs="0">4</count><count runs="1">4</count><count runs="2">1</count></situation>
<situation outs="2" runners="5" balls="3" strikes="0"><total>12</total><count runs="0">9</count><count runs="1">1</count><count runs="2">2</count></situation>
<situation outs="2" runners="5" balls="3" strikes="1"><total>5</total><count runs="0">4</count><count runs="1">0</count><count runs="2">1</count></situation>
<situation outs="2" runners="5" balls="3" strikes="2"><total>6</total><count runs="0">5</count><count runs="1">1</count></situation>
<situation outs="2" runners="3" balls="0" strikes="0"><total>30082</total><count runs="0">22942</count><count runs="1">5263</count><count runs="2">1274</count><count runs="3">402</count><count runs="4">133</count><count runs="5">49</count><count runs="6">14</count><count runs="7">3</count><count runs="8">1</count><count runs="9">1</count></situation>
<situation outs="2" runners="3" balls="0" strikes="1"><total>21</total><count runs="0">18</count><count runs="1">2</count><count runs="2">0</count><count runs="3">0</count><count runs="4">1</count></situation>
<situation outs="2" runners="3" balls="0" strikes="2"><total>10</total><count runs="0">9</count><count runs="1">0</count><count runs="2">0</count><count runs="3">0</count><count runs="4">1</count></situation>
<situation outs="2" runners="3" balls="1" strikes="0"><total>55</total><count runs="0">37</count><count runs="1">10</count><count runs="2">5</count><count runs="3">2</count><count runs="4">1</count></situation>
<situation outs="2" runners="3" balls="1" strikes="1"><total>23</total><count runs="0">18</count><count runs="1">4</count><count runs="2">1</count></situation>
<situation outs="2" runners="3" balls="1" strikes="2"><total>11</total><count runs="0">9</count><count runs="1">1</count><count runs="2">0</count><count runs="3">0</count><count runs="4">1</count></situation>
<situation outs="2" runners="3" balls="2" strikes="0"><total>36</total><count runs="0">24</count><count runs="1">5</count><count runs="2">4</count><count runs="3">2</count><count runs="4">1</count></situation>
<situation outs="2" runners="3" balls="2" strikes="1"><total>21</total><count runs="0">19</count><count runs="1">1</count><count runs="2">1</count></situation>
<situation outs="2" runners="3" balls="2" strikes="2"><total>14</total><count runs="0">11</count><count runs="1">1</count><count runs="2">1</count><count runs="3">0</count><count runs="4">1</count></situation>
<situation outs="2" runners="3" balls="3" strikes="0"><total>25</total><count runs="0">15</count><count runs="1">5</count><count runs="2">3</count><count runs="3">1</count><count runs="4">1</count></situation>
<situation outs="2" runners="3" balls="3" strikes="1"><total>18</total><count runs="0">15</count><count runs="1">2</count><count runs="2">0</count><count runs="3">0</count><count runs="4">1</count></situation>
<situation outs="2" runners="3" balls="3" strikes="2"><total>21</total><count runs="0">18</count><count runs="1">1</count><count runs="2">1</count><count runs="3">0</count><count runs="4">1</count></situation>
<situation outs="2" runners="7" balls="0" strikes="0"><total>8746</total><count runs="0">6163</count><count runs="1">545</count><count runs="2">1459</count><count runs="3">392</count><count runs="4">126</count><count runs="5">40</count><count runs="6">13</count><count runs="7">4</count><count runs="8">3</count><count runs="9">0</count><count runs="10">1</count></situation>
<situation outs="2" runners="7" balls="0" strikes="1"><total>16</total><count runs="0">10</count><count runs="1">2</count><count runs="2">3</count><count runs="3">1</count></situation>
<situation outs="2" runners="7" balls="0" strikes="2"><total>9</total><count runs="0">6</count><count runs="1">0</count><count runs="2">2</count><count runs="3">1</count></situation>
<situation outs="2" runners="7" balls="1" strikes="0"><total>22</total><count runs="0">17</count><count runs="1">1</count><count runs="2">3</count><count runs="3">1</count></situation>
<situation outs="2" runners="7" balls="1" strikes="1"><total>9</total><count runs="0">5</count><count runs="1">1</count><count runs="2">3</count></situation>
<situation outs="2" runners="7" balls="2" strikes="0"><total>14</total><count runs="0">13</count><count runs="1">0</count><count runs="2">0</count><count runs="3">1</count></situation>
<situation outs="2" runners="7" balls="3" strikes="0"><total>12</total><count runs="0">12</count></situation>
<situation outs="2" runners="7" balls="3" strikes="1"><total>3</total><count runs="0">3</count></situation>
<situation outs="2" runners="7" balls="3" strikes="2"><total>5</total><count runs="0">4</count><count runs="1">0</count><count runs="2">1</count></situation>
<situation outs="2" runners="2" balls="0" strikes="0"><total>52434</total><count runs="0">46146</count><count runs="1">3615</count><count runs="2">1776</count><count runs="3">605</count><count runs="4">198</count><count runs="5">57</count><count runs="6">23</count><count runs="7">11</count><count runs="8">3</count></situation>
<situation outs="2" runners="2" balls="0" strikes="1"><total>45</total><count runs="0">42</count><count runs="1">0</count><count runs="2">2</count><count runs="3">1</count></situation>
<situation outs="2" runners="2" balls="0" strikes="2"><total>18</total><count runs="0">17</count><count runs="1">0</count><count runs="2">1</count></situation>
<situation outs="2" runners="2" balls="1" strikes="0"><total>62</total><count runs="0">51</count><count runs="1">6</count><count runs="2">3</count><count runs="3">2</count></situation>
<situation outs="2" runners="2" balls="1" strikes="1"><total>44</total><count runs="0">36</count><count runs="1">2</count><count runs="2">4</count><count runs="3">2</count></situation>
<situation outs="2" runners="2" balls="1" strikes="2"><total>25</total><count runs="0">19</count><count runs="1">0</count><count runs="2">4</count><count runs="3">2</count></situation>
<situation outs="2" runners="2" balls="2" strikes="0"><total>28</total><count runs="0">25</count><count runs="1">2</count><count runs="2">0</count><count runs="3">1</count></situation>
<situation outs="2" runners="2" balls="2" strikes="1"><total>25</total><count runs="0">23</count><count runs="1">1</count><count runs="2">1</count></situation>
<situation outs="2" runners="2" balls="2" strikes="2"><total>21</total><count runs="0">16</count><count runs="1">1</count><count runs="2">3</count><count runs="3">1</count></situation>
<situation outs="2" runners="2" balls="3" strikes="0"><total>17</total><count runs="0">14</count><count runs="1">2</count><count runs="2">0</count><count runs="3">1</count></situation>
<situation outs="2" runners="2" balls="3" strikes="1"><total>14</total><count runs="0">13</count><count runs="1">0</count><count runs="2">1</count></situation>
<situation outs="2" runners="2" balls="3" strikes="2"><total>11</total><count runs="0">10</count><count runs="1">0</count><count runs="2">0</count><count runs="3">1</count></situation>
<situation outs="2" runners="6" balls="0" strikes="0"><total>11830</total><count runs="0">7927</count><count runs="1">2269</count><count runs="2">964</count><count runs="3">457</count><count runs="4">130</count><count runs="5">51</count><count runs="6">21</count><count runs="7">7</count><count runs="8">3</count><count runs="9">0</count><count runs="10">0</count><count runs="11">1</count></situation>
<situation outs="2" runners="6" balls="0" strikes="1"><total>19</total><count runs="0">12</count><count runs="1">2</count><count runs="2">2</count><count runs="3">3</count></situation>
<situation outs="2" runners="6" balls="0" strikes="2"><total>10</total><count runs="0">7</count><count runs="1">1</count><count runs="2">1</count><count runs="3">1</count></situation>
<situation outs="2" runners="6" balls="1" strikes="0"><total>18</total><count runs="0">12</count><count runs="1">1</count><count runs="2">1</count><count runs="3">4</count></situation>
<situation outs="2" runners="6" balls="2" strikes="0"><total>11</total><count runs="0">7</count><count runs="1">1</count><count runs="2">1</count><count runs="3">2</count></situation>
<situation outs="2" runners="6" balls="3" strikes="0"><total>10</total><count runs="0">7</count><count runs="1">1</count><count runs="2">1</count><count runs="3">1</count></situation>
<situation outs="2" runners="4" balls="0" strikes="0"><total>19393</total><count runs="0">14691</count><count runs="1">2381</count><count runs="2">1248</count><count runs="3">724</count><count runs="4">241</count><count runs="5">75</count><count runs="6">20</count><count runs="7">8</count><count runs="8">3</count><count runs="9">0</count><count runs="10">1</count><count runs="11">0</count><count runs="12">0</count><count runs="13">1</count></situation>
<situation outs="2" runners="4" balls="0" strikes="1"><total>37</total><count runs="0">30</count><count runs="1">4</count><count runs="2">1</count><count runs="3">1</count><count runs="4">1</count></situation>
<situation outs="2" runners="4" balls="0" strikes="2"><total>18</total><count runs="0">13</count><count runs="1">3</count><count runs="2">1</count><count runs="3">1</count></situation>
<situation outs="2" runners="4" balls="1" strikes="0"><total>46</total><count runs="0">29</count><count runs="1">4</count><count runs="2">5</count><count runs="3">5</count><count runs="4">0</count><count runs="5">2</count><count runs="6">0</count><count runs="7">1</count></situation>
<situation outs="2" runners="4" balls="1" strikes="1"><total>23</total><count runs="0">16</count><count runs="1">2</count><count runs="2">2</count><count runs="3">2</count><count runs="4">1</count></situation>
<situation outs="2" runners="4" balls="1" strikes="2"><total>16</total><count runs="0">13</count><count runs="1">2</count><count runs="2">0</count><count runs="3">1</count></situation>
<situation outs="2" runners="4" balls="2" strikes="0"><total>31</total><count runs="0">21</count><count runs="1">3</count><count runs="2">2</count><count runs="3">3</count><count runs="4">0</count><count runs="5">1</count><count runs="6">0</count><count runs="7">1</count></situation>
<situation outs="2" runners="4" balls="2" strikes="1"><total>20</total><count runs="0">13</count><count runs="1">3</count><count runs="2">2</count><count runs="3">1</count><count runs="4">1</count></situation>
<situation outs="2" runners="4" balls="2" strikes="2"><total>15</total><count runs="0">10</count><count runs="1">2</count><count runs="2">1</count><count runs="3">1</count><count runs="4">1</count></situation>
<situation outs="2" runners="4" balls="3" strikes="0"><total>17</total><count runs="0">13</count><count runs="1">2</count><count runs="2">1</count><count runs="3">0</count><count runs="4">0</count><count runs="5">1</count></situation>
<situation outs="2" runners="4" balls="3" strikes="1"><total>9</total><count runs="0">7</count><count runs="1">0</count><count runs="2">1</count><count runs="3">1</count></situation>
<situation outs="2" runners="4" balls="3" strikes="2"><total>14</total><count runs="0">9</count><count runs="1">1</count><count runs="2">2</count><count runs="3">1</count><count runs="4">1</count></situation>
<situation outs="2" runners="8" balls="0" strikes="0"><total>6532</total><count runs="0">4276</count><count runs="1">696</count><count runs="2">757</count><count runs="3">435</count><count runs="4">257</count><count runs="5">75</count><count runs="6">22</count><count runs="7">8</count><count runs="8">4</count><count runs="9">0</count><count runs="10">1</count><count runs="11">0</count><count runs="12">0</count><count runs="13">1</count></situation>
<situation outs="2" runners="8" balls="0" strikes="1"><total>16</total><count runs="0">9</count><count runs="1">0</count><count runs="2">3</count><count runs="3">2</count><count runs="4">1</count><count runs="5">1</count></situation>
<situation outs="2" runners="8" balls="0" strikes="2"><total>9</total><count runs="0">7</count><count runs="1">0</count><count runs="2">1</count><count runs="3">0</count><count runs="4">0</count><count runs="5">1</count></situation>
<situation outs="2" runners="8" balls="1" strikes="0"><total>23</total><count runs="0">10</count><count runs="1">5</count><count runs="2">2</count><count runs="3">5</count><count runs="4">0</count><count runs="5">1</count></situation>
<situation outs="2" runners="8" balls="1" strikes="1"><total>10</total><count runs="0">4</count><count runs="1">0</count><count runs="2">3</count><count runs="3">3</count></situation>
<situation outs="2" runners="8" balls="1" strikes="2"><total>7</total><count runs="0">3</count><count runs="1">0</count><count runs="2">2</count><count runs="3">1</count><count runs="4">0</count><count runs="5">1</count></situation>
<situation outs="2" runners="8" balls="2" strikes="0"><total>17</total><count runs="0">7</count><count runs="1">5</count><count runs="2">1</count><count runs="3">3</count><count runs="4">0</count><count runs="5">1</count></situation>
<situation outs="2" runners="8" balls="2" strikes="2"><total>8</total><count runs="0">4</count><count runs="1">1</count><count runs="2">1</count><count runs="3">2</count></situation>
<situation outs="2" runners="8" balls="3" strikes="0"><total>12</total><count runs="0">4</count><count runs="1">4</count><count runs="2">0</count><count runs="3">3</count><count runs="4">0</count><count runs="5">1</count></situation>
<situation outs="2" runners="8" balls="3" strikes="1"><total>5</total><count runs="0">4</count><count runs="1">0</count><count runs="2">0</count><count runs="3">1</count></situation>
<situation outs="2" runners="8" balls="3" strikes="2"><total>6</total><count runs="0">3</count><count runs="1">1</count><count runs="2">0</count><count runs="3">2</count></situation>
</situations>
